spatialWeb/__init__.py
spatialWeb/gem2mtx.py
spatialWeb/utils.py
spatialWeb-0.0.3.dist-info/METADATA
spatialWeb-0.0.3.dist-info/WHEEL
spatialWeb-0.0.3.dist-info/top_level.txt
spatialWeb-0.0.3.dist-info/RECORD
